Metadata-Version: 1.0
Name: hirosql
Version: 0.2
Summary: A small development tool for mysql or other databases
Home-page: UNKNOWN
Author: Hiroyuki Ishii
Author-email: hiroyuki.ishii.42@gmail.com
License: UNKNOWN
Keywords: sql
Platform: UNKNOWN
